{
    "service":{
        "port":"localhost:8302"
    },
    "crv":{
        "server":"http://127.0.0.1:8200",
        "appID":"smartlock",
        "token":"lockapi"
    },
    "i6000":{
        "findWorkTicket":"http://21.11.7.20/i6000-dyjtwoticket-service/i6000-api/findWorkTicket",
        "selectInvolveSystemInfo":"http://21.11.7.20/i6000-dyj-service/api/wf/i6000-api/selectInvolveSystemInfo",
        "selectInvolveDeviceInfo":"http://21.11.7.20/i6000-dyj-service/api/wf/i6000-api/selectInvolveDeviceInfo",
        "getSignDataUrl":"http://121.37.185.248:8910/sg/signData",
        "queryInterval":"10h",
        "allOrgIds":[""],
        "beginDateDiff":-3,
        "newWorkTicketStatusLabel":"工作票许可",
        "updateWorkTicketStatusValue":"变更与延期"
    }
}